sat_unittest_dataprovider/__init__.py
tests/__init__.py
tests/data_providers.py
tests/real_world_example.py
tests/test_data_provider.py
tests/test_readme_examples.py
sat_unittest_dataprovider-1.0.1.dist-info/METADATA
sat_unittest_dataprovider-1.0.1.dist-info/WHEEL
sat_unittest_dataprovider-1.0.1.dist-info/top_level.txt
sat_unittest_dataprovider-1.0.1.dist-info/RECORD
